{
  "Service": "Get TTA",
  "Persona": "Student",
  "First Name": "Jeanine",
  "Surname": "Ward",
  "Email": "tonette@example.net",
  "Returner": "No",
  "Degree": "I'm studying for a degree",
  "Study year": "First year",
  "Degree subject": "Biology",
  "Degree class": "First class",
  "Stage of Interest": "Secondary",
  "Grade 4 English and Maths": "Yes",
  "Interested subject": "English",
  "Desired start": "2022",
  "Date of Birth": "1985-12-25T00:00:00.000+00:00",
  "Where live": "UK",
  "Address line 1": "996 Jess Roads",
  "Address line 2": "Suite 117",
  "Town or city": "Willmsmouth",
  "Postcode": "EV06 3EJ",
  "Telephone": "0952 692 3359",
  "Final Journey Status": "COMPLETE",
  "apiSubmission": {
    "countryId": "0df4c2e6-74f9-e811-a97a-000d3a2760f2",
    "preferredEducationPhaseId": 222750001,
    "firstName": "Jeanine",
    "lastName": "Ward",
    "email": "tonette@example.net",
    "degreeStatusId": 222750003,
    "degreeSubject": "802655a1-2afa-e811-a981-000d3a276620",
    "ukDegreeGradeId": 222750001,
    "hasGcseMathsAndEnglishId": 222750000,
    "preferredTeachingSubjectId": "942655a1-2afa-e811-a981-000d3a276620",
    "initialTeacherTrainingYearId": 22304,
    "dateOfBirth": "1985-12-25T00:00:00.000+00:00",
    "addressLine1": "996 Jess Roads",
    "addressLine2": "Suite 117",
    "addressCity": "Willmsmouth",
    "addressPostcode": "EV06 3EJ",
    "telephone": "0952 692 3359",
    "degreeTypeId": 222750000,
    "acceptedPolicyId": "0a203956-e935-ea11-a813-000d3a44a8e9"
  }
}