{
  "Service": "Get TTA",
  "Persona": "Graduate",
  "First Name": "Julia",
  "Surname": "Hilll",
  "Email": "talisha@example.net",
  "Returner": "No",
  "Degree": "Yes",
  "Degree subject": "Maths",
  "Degree class": "First class",
  "Stage of Interest": "Secondary",
  "Grade 4 English and Maths": "Yes",
  "Grade 4 Science": "Yes",
  "Interested subject": "Biology",
  "Desired start": "2021",
  "Date of Birth": "1983-12-25T00:00:00.000+00:00",
  "Where live": "UK",
  "Address line 1": "64936 Tatum Shoals",
  "Address line 2": "Suite 798",
  "Town or city": "Mayertfurt",
  "Postcode": "K7 2LQ",
  "Telephone": "0329 550 8745",
  "Final Journey Status": "COMPLETE",
  "apiSubmission": {
    "countryId": "0df4c2e6-74f9-e811-a97a-000d3a2760f2",
    "preferredEducationPhaseId": 222750001,
    "firstName": "Julia",
    "lastName": "Hilll",
    "email": "talisha@example.net",
    "degreeStatusId": 222750000,
    "degreeSubject": "a42655a1-2afa-e811-a981-000d3a276620",
    "ukDegreeGradeId": 222750001,
    "hasGcseMathsAndEnglishId": 222750000,
    "hasGcseScienceId": 222750000,
    "preferredTeachingSubjectId": "802655a1-2afa-e811-a981-000d3a276620",
    "initialTeacherTrainingYearId": 22303,
    "dateOfBirth": "1983-12-25T00:00:00.000+00:00",
    "addressLine1": "64936 Tatum Shoals",
    "addressLine2": "Suite 798",
    "addressCity": "Mayertfurt",
    "addressPostcode": "K7 2LQ",
    "telephone": "0329 550 8745",
    "acceptedPolicyId": "0a203956-e935-ea11-a813-000d3a44a8e9",
    "degreeTypeId": 222750000
  }
}